{"v":4,"entries":{"configure-your-project--docs":{"id":"configure-your-project--docs","title":"Configure your project","name":"Docs","importPath":"./src/stories/Configure.mdx","storiesImports":[],"type":"docs","tags":["unattached-mdx","docs"]},"components-slider--docs":{"id":"components-slider--docs","title":"Components/Slider","name":"Docs","importPath":"./src/stories/Slider.stories.jsx","type":"docs","tags":["autodocs","docs"],"storiesImports":[]},"components-slider--continuous":{"type":"story","id":"components-slider--continuous","name":"Continuous","title":"Components/Slider","importPath":"./src/stories/Slider.stories.jsx","tags":["autodocs","story"]},"components-slider--discrete":{"type":"story","id":"components-slider--discrete","name":"Discrete","title":"Components/Slider","importPath":"./src/stories/Slider.stories.jsx","tags":["autodocs","story"]},"components-slider--range":{"type":"story","id":"components-slider--range","name":"Range","title":"Components/Slider","importPath":"./src/stories/Slider.stories.jsx","tags":["autodocs","story"]}}}
